LICENSE
MANIFEST.in
README.rst
setup.py
bootlog/__init__.py
bootlog/admin.py
bootlog/models.py
bootlog/search_indexes.py
bootlog/tests.py
bootlog/urls.py
bootlog/views.py
bootlog/static/css/bootstrap-theme.css
bootlog/static/css/bootstrap-theme.css.map
bootlog/static/css/bootstrap-theme.min.css
bootlog/static/css/bootstrap.css
bootlog/static/css/bootstrap.css.map
bootlog/static/css/bootstrap.min.css
bootlog/static/css/mycss.css
bootlog/static/css/style.css
bootlog/static/fonts/glyphicons-halflings-regular.eot
bootlog/static/fonts/glyphicons-halflings-regular.svg
bootlog/static/fonts/glyphicons-halflings-regular.ttf
bootlog/static/fonts/glyphicons-halflings-regular.woff
bootlog/static/img/apple-touch-icon-114-precomposed.png
bootlog/static/img/apple-touch-icon-144-precomposed.png
bootlog/static/img/apple-touch-icon-57-precomposed.png
bootlog/static/img/apple-touch-icon-72-precomposed.png
bootlog/static/img/favicon.png
bootlog/static/img/glyphicons-halflings-white.png
bootlog/static/img/glyphicons-halflings.png
bootlog/static/js/bootstrap.js
bootlog/static/js/bootstrap.min.js
bootlog/static/js/html5shiv.js
bootlog/static/js/jquery.min.js
bootlog/static/js/less-1.3.3.min.js
bootlog/static/js/scripts.js
bootlog/templates/bootlog/404.html
bootlog/templates/bootlog/about_us.html
bootlog/templates/bootlog/base.html
bootlog/templates/bootlog/comment_form.html
bootlog/templates/bootlog/footer_row.html
bootlog/templates/bootlog/form.html
bootlog/templates/bootlog/head.html
bootlog/templates/bootlog/jscript_html.html
bootlog/templates/bootlog/left_sidebar.html
bootlog/templates/bootlog/mid_col_post_cat.html
bootlog/templates/bootlog/mid_col_post_col.html
bootlog/templates/bootlog/mid_column.html
bootlog/templates/bootlog/post.html
bootlog/templates/bootlog/series_html.html
bootlog/templates/bootlog/side_panel.html
bootlog/templates/bootlog/top_row.html
bootlog/templates/bootlog/tri_stack.html
bootlog/templates/bootlog/tri_stack_series.html
bootlog/templates/search/search.html
django_bootlog.egg-info/PKG-INFO
django_bootlog.egg-info/SOURCES.txt
django_bootlog.egg-info/dependency_links.txt
django_bootlog.egg-info/top_level.txt