Metadata-Version: 1.1
Name: django-bootlog
Version: 1.0.0
Summary: A Django Blogging App based on Twitter Bootstrap Theme
Home-page: entworks.in
Author: Ent
Author-email: last_ent@outlook.com
License: New BSD License
Platform: UNKNOWN
Classifier: Environment :: Web Environment
Classifier: Framework :: Django
Classifier: Intended Audience :: Developers
Classifier: License :: OSI Approved :: BSD License
Classifier: Operating System :: OS Independent
Classifier: Programming Language :: Python
Classifier: Programming Language :: Python :: 2.6
Classifier: Programming Language :: Python :: 2.7
Classifier: Topic :: Internet :: WWW/HTTP
Classifier: Topic :: Internet :: WWW/HTTP :: Dynamic Content
